Metadata-Version: 2.1
Name: api_emissions_tracker
Version: 0.0.5
Summary: Estimates emissions linked to AI cloud services.
Home-page: https://github.com/borisruf/api_emissions_tracker
Author: Boris Ruf
License-File: LICENSE
Requires-Dist: wrapt
Requires-Dist: importlib
